dpipe/__init__.py
dvpipe/__init__.py
dvpipe-0.0.4.dist-info/LICENSE
dvpipe-0.0.4.dist-info/METADATA
dvpipe-0.0.4.dist-info/WHEEL
dvpipe-0.0.4.dist-info/top_level.txt
dvpipe-0.0.4.dist-info/RECORD
