Metadata-Version: 2.1
Name: dvpipe
Version: 0.0.4
Summary: A small Python utility that pipes data from function to function in sequencial order.
Home-page: https://github.com/chrisdiana/dvpipe
Author: Chris Diana
Author-email: cdiana.media@gmail.com
License: UNKNOWN
Platform: UNKNOWN
Classifier: Programming Language :: Python :: 3
Classifier: License :: OSI Approved :: MIT License
Classifier: Operating System :: OS Independent
Requires-Python: >=3.0
